lbank/__init__.py
lbank/__version__.py
lbank/api.py
lbank/error.py
lbank/old_api.py
lbank/utils.py
lbank/spot/__init__.py
lbank/spot/_account.py
lbank/spot/_base_data.py
lbank/spot/_market.py
lbank/spot/_order.py
lbank/spot/_trade.py
lbank/spot/_wallet.py
lbank/spot/_withdraw.py
lbank/websocket/__init__.py
lbank/websocket/base_lbank_socket.py
lbank/websocket/websocket_client.py
lbank_connector_python-1.0.137.dist-info/LICENSE.md
lbank_connector_python-1.0.137.dist-info/METADATA
lbank_connector_python-1.0.137.dist-info/WHEEL
lbank_connector_python-1.0.137.dist-info/top_level.txt
lbank_connector_python-1.0.137.dist-info/RECORD
